postgres_data_faker/__init__.py
postgres_data_faker/data_faker.py
postgres_data_faker-1.1.2.dist-info/METADATA
postgres_data_faker-1.1.2.dist-info/WHEEL
postgres_data_faker-1.1.2.dist-info/RECORD
