Metadata-Version: 2.1
Name: postgres-data-faker
Version: 1.1.2
Summary: Dummy and simple faker sensitive data for postgres database
Author: Borteq2
Author-email: borteq2@yandex.ru
Requires-Python: >=3.10,<4.0
Classifier: Programming Language :: Python :: 3
Classifier: Programming Language :: Python :: 3.10
Classifier: Programming Language :: Python :: 3.11
Requires-Dist: faker (>=18.4.0,<19.0.0)
Requires-Dist: psycopg2 (>=2.9.6,<3.0.0)
